MANIFEST.in
README.rst
setup.py
django_hyperadmin.egg-info/PKG-INFO
django_hyperadmin.egg-info/SOURCES.txt
django_hyperadmin.egg-info/dependency_links.txt
django_hyperadmin.egg-info/not-zip-safe
django_hyperadmin.egg-info/requires.txt
django_hyperadmin.egg-info/top_level.txt
hyperadmin/__init__.py
hyperadmin/apirequests.py
hyperadmin/app_settings.py
hyperadmin/datataps.py
hyperadmin/endpoints.py
hyperadmin/filters.py
hyperadmin/hyperobjects.py
hyperadmin/indexes.py
hyperadmin/links.py
hyperadmin/models.py
hyperadmin/signals.py
hyperadmin/sites.py
hyperadmin/states.py
hyperadmin/throttle.py
hyperadmin/urls.py
hyperadmin/views.py
hyperadmin/clients/__init__.py
hyperadmin/clients/common.py
hyperadmin/clients/djangoviews.py
hyperadmin/clients/mediatype.py
hyperadmin/clients/views/__init__.py
hyperadmin/clients/views/common.py
hyperadmin/clients/views/detail.py
hyperadmin/clients/views/edit.py
hyperadmin/clients/views/list.py
hyperadmin/contrib/__init__.py
hyperadmin/contrib/apikey/__init__.py
hyperadmin/contrib/apikey/apirequests.py
hyperadmin/contrib/apikey/common.py
hyperadmin/contrib/apikey/models.py
hyperadmin/contrib/apikey/resources.py
hyperadmin/contrib/apikey/tests/__init__.py
hyperadmin/contrib/apikey/tests/test_apikey.py
hyperadmin/mediatypes/__init__.py
hyperadmin/mediatypes/collectionjson.py
hyperadmin/mediatypes/common.py
hyperadmin/mediatypes/datatap.py
hyperadmin/mediatypes/encoders.py
hyperadmin/mediatypes/haljson.py
hyperadmin/mediatypes/html5.py
hyperadmin/mediatypes/iframe.py
hyperadmin/mediatypes/json.py
hyperadmin/mediatypes/passthrough.py
hyperadmin/resources/__init__.py
hyperadmin/resources/endpoints.py
hyperadmin/resources/hyperobjects.py
hyperadmin/resources/resources.py
hyperadmin/resources/auth/__init__.py
hyperadmin/resources/auth/endpoints.py
hyperadmin/resources/auth/forms.py
hyperadmin/resources/auth/resources.py
hyperadmin/resources/crud/__init__.py
hyperadmin/resources/crud/endpoints.py
hyperadmin/resources/crud/hyperobjects.py
hyperadmin/resources/crud/resources.py
hyperadmin/resources/directory/__init__.py
hyperadmin/resources/directory/endpoints.py
hyperadmin/resources/directory/forms.py
hyperadmin/resources/directory/resources.py
hyperadmin/resources/directory/site.py
