Metadata-Version: 1.1
Name: django-hyperadmin
Version: 0.10.0
Summary: A hypermedia API framework for Django.
Home-page: http://github.com/webcube/django-hyperadmin
Author: Jason Kraus
Author-email: zbyte64@gmail.com
License: New BSD License
Keywords: django hypermedia HATEOAS REST
Platform: UNKNOWN
Classifier: Programming Language :: Python
Classifier: Environment :: Web Environment
Classifier: Framework :: Django
Classifier: Operating System :: OS Independent
Classifier: Natural Language :: English
Classifier: Development Status :: 4 - Beta
Classifier: Intended Audience :: Developers
Classifier: License :: OSI Approved :: BSD License
Classifier: Topic :: Internet :: WWW/HTTP :: Dynamic Content
